python_database_rest_logging/__init__.py
python_database_rest_logging/__main__.py
python_database_rest_logging/config.py
python_database_rest_logging/handler.py
python_database_rest_logging/utils.py
python_database_rest_logging/api/LoggingAPI.py
python_database_rest_logging/api/VersionAPI.py
python_database_rest_logging/api/__init__.py
python_database_rest_logging/model/__init__.py
python_database_rest_logging/services/CrudService.py
python_database_rest_logging/services/LogEntryService.py
python_database_rest_logging/services/LogService.py
python_database_rest_logging/services/__init__.py
python_database_rest_logging-1.0.5.dist-info/METADATA
python_database_rest_logging-1.0.5.dist-info/RECORD
python_database_rest_logging-1.0.5.dist-info/WHEEL
python_database_rest_logging-1.0.5.dist-info/top_level.txt
