Metadata-Version: 2.1
Name: python-database-rest-logging
Version: 1.0.5
Summary: Python database rest logging
Home-page: http://marcomendao.betacode.tech
Author: Marco Mendao
Author-email: mac.mendao@gmail.com
License: UNKNOWN
Platform: UNKNOWN
Requires-Dist: Flask (==0.12)
Requires-Dist: Flask-HTTPAuth (==3.2.2)
Requires-Dist: Flask-RESTful (==0.3.5)
Requires-Dist: flask-security (==1.7.5)
Requires-Dist: flask-cors (==3.0.2)
Requires-Dist: pony (==0.7.6)
Requires-Dist: graphviz
Requires-Dist: pymysql
Requires-Dist: networkx
Requires-Dist: defusedxml
Requires-Dist: requests
Requires-Dist: flask-injector
Requires-Dist: injector
